{
  "posts": [
    {
      "id": 1,
      "title": "hello"
    }
  ],
  "profile": {
    "name": "typicode"
  },
  "matrix":{
      "count":5,
      "products":[
        {"id":1,"productName":"P1", "categoryName":"C1"},
        {"id":5,"productName":"P5", "categoryName":"C1"},
        {"id":8,"productName":"P8", "categoryName":"C2"},
        {"id":11,"productName":"P11", "categoryName":"C2"},
        {"id":14,"productName":"P14", "categoryName":"C3"}
        ],
      "compatibility":[
      {
        "product":{"id":1,"productName":"P1", "categoryName":"C1"},
        "compatibleWith":[
          {"id":1,"productName":"P1", "categoryName":"C1"},
          {"id":8,"productName":"P8", "categoryName":"C2"}
        ]
      },
      {
        "product":{"id":5,"productName":"P5", "categoryName":"C1"},
        "compatibleWith":[
          {"id":5,"productName":"P5", "categoryName":"C1"},
          {"id":11,"productName":"P11", "categoryName":"C2"}
        ]
      },
      {
        "product":{"id":8,"productName":"P8", "categoryName":"C2"},
        "compatibleWith":[
          {"id":1,"productName":"P1", "categoryName":"C1"},
          {"id":8,"productName":"P8", "categoryName":"C2"}
        ]
      },
      {
        "product":{"id":11,"productName":"P11", "categoryName":"C2"},
        "compatibleWith":[
          {"id":11,"productName":"P11", "categoryName":"C2"},
          {"id":5,"productName":"P5", "categoryName":"C1"}
        ]
      },
      {
        "product":{"id":14,"productName":"P14", "categoryName":"C3"},
        "compatibleWith":[
          {"id":14,"productName":"P14", "categoryName":"C3"}
        ]
      }
     ]
  }
}
